MANIFEST.in
README.md
setup.py
degate/__init__.py
degate/__version__.py
degate/api.py
degate/error.py
degate/lib/__init__.py
degate/lib/degate.dll
degate/lib/degate_linux.so
degate/lib/degate_mac.so
degate/lib/degate_mac_m1.so
degate/lib/enums.py
degate/lib/libgo.py
degate/lib/utils.py
degate/spot/__init__.py
degate/spot/account.py
degate/spot/data_stream.py
degate/spot/market.py
degate/spot/wallet.py
degate/websocket/__init__.py
degate/websocket/degate_client_factory.py
degate/websocket/degate_client_protocol.py
degate/websocket/degate_socket_manager.py
degate/websocket/websocket_client.py
degate/websocket/spot/__init__.py
degate/websocket/spot/websocket_client.py
degate_connector.egg-info/PKG-INFO
degate_connector.egg-info/SOURCES.txt
degate_connector.egg-info/dependency_links.txt
degate_connector.egg-info/requires.txt
degate_connector.egg-info/top_level.txt
requirements/requirements.txt