Metadata-Version: 2.1
Name: degate-connector
Version: 1.2.1
Summary: This is a lightweight library that works as a connector to DeGate public SDK.
Home-page: https://github.com/degatedev/degate-sdk-python.git
Author: DeGate
License: MIT
Keywords: degate,Public SDK
Platform: UNKNOWN
Classifier: Intended Audience :: Developers
Classifier: License :: OSI Approved :: MIT License
Classifier: Programming Language :: Python :: 3.6
Classifier: Programming Language :: Python :: 3.7
Classifier: Programming Language :: Python :: 3.8
Classifier: Programming Language :: Python :: 3.9
Classifier: Programming Language :: Python :: 3.10
Requires-Python: >=3.6
